OpenOPC/__init__.py
OpenOPC/common.py
OpenOPC/opc.py
OpenOPC/opcda.py
OpenOPC/opcdaio.py
OpenOPC/opcdatools.py
OpenOPC/systemhealth.py
OpenOPC_DA-1.5.1.dist-info/LICENSE.txt
OpenOPC_DA-1.5.1.dist-info/METADATA
OpenOPC_DA-1.5.1.dist-info/WHEEL
OpenOPC_DA-1.5.1.dist-info/entry_points.txt
OpenOPC_DA-1.5.1.dist-info/top_level.txt
OpenOPC_DA-1.5.1.dist-info/RECORD
