Metadata-Version: 2.1
Name: OpenOPC-DA
Version: 1.5.1
Summary: OPC-DA (OLE for Process Control) toolkit for Python 3.7+
Home-page: https://github.com/j3mg/openopc
Author: j3mg
License: GPLv2
Keywords: python,opc,opc-da,openopc
Classifier: Development Status :: 5 - Production/Stable
Classifier: Intended Audience :: Developers
Classifier: License :: OSI Approved :: GNU General Public License v2 or later (GPLv2+)
Classifier: Natural Language :: English
Classifier: Operating System :: OS Independent
Classifier: Programming Language :: Python :: 3
Classifier: Programming Language :: Python :: 3.7
Classifier: Programming Language :: Python :: 3.8
Classifier: Programming Language :: Python :: 3.9
Classifier: Programming Language :: Python :: 3.10
Classifier: Topic :: System :: Distributed Computing
Classifier: Topic :: System :: Networking
Requires-Python: >=3.4
License-File: LICENSE.txt
Requires-Dist: Pyro5 (>=5.13.1)
